{"commitInfo":{"timestamp":1767539222384,"operation":"MERGE","operationParameters":{"predicate":"[\"((shelf_id#102581 = shelf_id#102543) AND (batch_code#102582 = batch_code#102544))\"]","matchedPredicates":"[{\"actionType\":\"update\"}]","notMatchedPredicates":"[]","notMatchedBySourcePredicates":"[]"},"readVersion":526,"isolationLevel":"Serializable","isBlindAppend":false,"operationMetrics":{"numTargetRowsCopied":"7333","numTargetRowsDeleted":"0","numTargetFilesAdded":"1","numTargetBytesAdded":"133985","numTargetBytesRemoved":"133956","numTargetDeletionVectorsAdded":"0","numTargetRowsMatchedUpdated":"214","executionTimeMs":"3873","numTargetRowsInserted":"0","numTargetRowsMatchedDeleted":"0","numTargetDeletionVectorsUpdated":"0","scanTimeMs":"1511","numTargetRowsUpdated":"214","numOutputRows":"7547","numTargetDeletionVectorsRemoved":"0","numTargetRowsNotMatchedBySourceUpdated":"0","numTargetChangeFilesAdded":"0","numSourceRows":"214","numTargetFilesRemoved":"1","numTargetRowsNotMatchedBySourceDeleted":"0","rewriteTimeMs":"797"},"engineInfo":"Apache-Spark/3.5.1 Delta-Lake/3.2.0","txnId":"ace402df-28e9-42b2-aa4b-b21e4f172d15"}}
{"add":{"path":"part-00000-4fa98fc7-ac9e-4fdc-bedd-8e3052a9c396-c000.snappy.parquet","partitionValues":{},"size":133985,"modificationTime":1767539222363,"dataChange":true,"stats":"{\"numRecords\":7547,\"minValues\":{\"shelf_id\":\"BABBAB2856\",\"batch_code\":\"B0000001\",\"received_date\":\"2025-11-17\",\"expiry_date\":\"2026-11-26\",\"batch_quantity_store\":-12,\"last_update_ts\":\"2025-10-01T01:48:40.000Z\"},\"maxValues\":{\"shelf_id\":\"WINWHI0806\",\"batch_code\":\"B0007547\",\"received_date\":\"2025-11-26\",\"expiry_date\":\"2029-10-25\",\"batch_quantity_store\":76,\"last_update_ts\":\"2025-10-03T03:54:05.000Z\"},\"nullCount\":{\"shelf_id\":0,\"batch_code\":0,\"received_date\":0,\"expiry_date\":0,\"batch_quantity_store\":0,\"last_update_ts\":0}}"}}
{"remove":{"path":"part-00000-3a1979bb-3611-4397-a061-f7c5d31486e1-c000.snappy.parquet","deletionTimestamp":1767539222383,"dataChange":true,"extendedFileMetadata":true,"partitionValues":{},"size":133956,"stats":"{\"numRecords\":7547}"}}
