{"commitInfo":{"timestamp":1767539168750,"operation":"MERGE","operationParameters":{"predicate":"[\"((shelf_id#90738 = shelf_id#90700) AND (batch_code#90739 = batch_code#90701))\"]","matchedPredicates":"[{\"actionType\":\"update\"}]","notMatchedPredicates":"[]","notMatchedBySourcePredicates":"[]"},"readVersion":522,"isolationLevel":"Serializable","isBlindAppend":false,"operationMetrics":{"numTargetRowsCopied":"7459","numTargetRowsDeleted":"0","numTargetFilesAdded":"1","numTargetBytesAdded":"133905","numTargetBytesRemoved":"133889","numTargetDeletionVectorsAdded":"0","numTargetRowsMatchedUpdated":"88","executionTimeMs":"2488","numTargetRowsInserted":"0","numTargetRowsMatchedDeleted":"0","numTargetDeletionVectorsUpdated":"0","scanTimeMs":"868","numTargetRowsUpdated":"88","numOutputRows":"7547","numTargetDeletionVectorsRemoved":"0","numTargetRowsNotMatchedBySourceUpdated":"0","numTargetChangeFilesAdded":"0","numSourceRows":"88","numTargetFilesRemoved":"1","numTargetRowsNotMatchedBySourceDeleted":"0","rewriteTimeMs":"442"},"engineInfo":"Apache-Spark/3.5.1 Delta-Lake/3.2.0","txnId":"2da7e980-5027-4f6d-90ed-18a1527e73c5"}}
{"add":{"path":"part-00000-cee01a7b-6560-4774-90d4-5c69cf120deb-c000.snappy.parquet","partitionValues":{},"size":133905,"modificationTime":1767539168741,"dataChange":true,"stats":"{\"numRecords\":7547,\"minValues\":{\"shelf_id\":\"BABBAB2856\",\"batch_code\":\"B0000001\",\"received_date\":\"2025-11-17\",\"expiry_date\":\"2026-11-26\",\"batch_quantity_store\":-12,\"last_update_ts\":\"2025-10-01T01:48:40.000Z\"},\"maxValues\":{\"shelf_id\":\"WINWHI0806\",\"batch_code\":\"B0007547\",\"received_date\":\"2025-11-26\",\"expiry_date\":\"2029-10-25\",\"batch_quantity_store\":76,\"last_update_ts\":\"2025-10-03T03:54:05.000Z\"},\"nullCount\":{\"shelf_id\":0,\"batch_code\":0,\"received_date\":0,\"expiry_date\":0,\"batch_quantity_store\":0,\"last_update_ts\":0}}"}}
{"remove":{"path":"part-00000-4ad6b41d-2220-4d15-a931-107a70c45802-c000.snappy.parquet","deletionTimestamp":1767539168748,"dataChange":true,"extendedFileMetadata":true,"partitionValues":{},"size":133889,"stats":"{\"numRecords\":7547}"}}
