{"commitInfo":{"timestamp":1767540558631,"operation":"MERGE","operationParameters":{"predicate":"[\"((shelf_id#72902 = shelf_id#72864) AND (batch_code#72903 = batch_code#72865))\"]","matchedPredicates":"[{\"actionType\":\"update\"}]","notMatchedPredicates":"[]","notMatchedBySourcePredicates":"[]"},"readVersion":596,"isolationLevel":"Serializable","isBlindAppend":false,"operationMetrics":{"numTargetRowsCopied":"7514","numTargetRowsDeleted":"0","numTargetFilesAdded":"1","numTargetBytesAdded":"134651","numTargetBytesRemoved":"134649","numTargetDeletionVectorsAdded":"0","numTargetRowsMatchedUpdated":"33","executionTimeMs":"2543","numTargetRowsInserted":"0","numTargetRowsMatchedDeleted":"0","numTargetDeletionVectorsUpdated":"0","scanTimeMs":"876","numTargetRowsUpdated":"33","numOutputRows":"7547","numTargetDeletionVectorsRemoved":"0","numTargetRowsNotMatchedBySourceUpdated":"0","numTargetChangeFilesAdded":"0","numSourceRows":"33","numTargetFilesRemoved":"1","numTargetRowsNotMatchedBySourceDeleted":"0","rewriteTimeMs":"395"},"engineInfo":"Apache-Spark/3.5.1 Delta-Lake/3.2.0","txnId":"7d71bd26-aa9f-4669-9079-9f6cd564bfc4"}}
{"add":{"path":"part-00000-00b7d758-1ad6-40f0-8801-4c8851a22ab9-c000.snappy.parquet","partitionValues":{},"size":134651,"modificationTime":1767540558623,"dataChange":true,"stats":"{\"numRecords\":7547,\"minValues\":{\"shelf_id\":\"BABBAB2856\",\"batch_code\":\"B0000001\",\"received_date\":\"2025-11-17\",\"expiry_date\":\"2026-11-26\",\"batch_quantity_store\":-18,\"last_update_ts\":\"2025-10-01T01:48:40.000Z\"},\"maxValues\":{\"shelf_id\":\"WINWHI0806\",\"batch_code\":\"B0007547\",\"received_date\":\"2025-11-26\",\"expiry_date\":\"2029-10-25\",\"batch_quantity_store\":76,\"last_update_ts\":\"2025-10-03T03:54:05.000Z\"},\"nullCount\":{\"shelf_id\":0,\"batch_code\":0,\"received_date\":0,\"expiry_date\":0,\"batch_quantity_store\":0,\"last_update_ts\":0}}"}}
{"remove":{"path":"part-00000-fb1c57c4-8118-4430-b620-a3fe7b78d355-c000.snappy.parquet","deletionTimestamp":1767540558631,"dataChange":true,"extendedFileMetadata":true,"partitionValues":{},"size":134649,"stats":"{\"numRecords\":7547}"}}
