{"commitInfo":{"timestamp":1767544278554,"operation":"MERGE","operationParameters":{"predicate":"[\"((shelf_id#58849 = shelf_id#58811) AND (batch_code#58850 = batch_code#58812))\"]","matchedPredicates":"[{\"actionType\":\"update\"}]","notMatchedPredicates":"[]","notMatchedBySourcePredicates":"[]"},"readVersion":865,"isolationLevel":"Serializable","isBlindAppend":false,"operationMetrics":{"numTargetRowsCopied":"7540","numTargetRowsDeleted":"0","numTargetFilesAdded":"1","numTargetBytesAdded":"136154","numTargetBytesRemoved":"136153","numTargetDeletionVectorsAdded":"0","numTargetRowsMatchedUpdated":"7","executionTimeMs":"2209","numTargetRowsInserted":"0","numTargetRowsMatchedDeleted":"0","numTargetDeletionVectorsUpdated":"0","scanTimeMs":"757","numTargetRowsUpdated":"7","numOutputRows":"7547","numTargetDeletionVectorsRemoved":"0","numTargetRowsNotMatchedBySourceUpdated":"0","numTargetChangeFilesAdded":"0","numSourceRows":"7","numTargetFilesRemoved":"1","numTargetRowsNotMatchedBySourceDeleted":"0","rewriteTimeMs":"260"},"engineInfo":"Apache-Spark/3.5.1 Delta-Lake/3.2.0","txnId":"f7e47be1-4c22-41aa-95ce-460b15621f38"}}
{"add":{"path":"part-00000-74333008-7b77-46dd-8bca-8c030b14f82a-c000.snappy.parquet","partitionValues":{},"size":136154,"modificationTime":1767544278543,"dataChange":true,"stats":"{\"numRecords\":7547,\"minValues\":{\"shelf_id\":\"BABBAB2856\",\"batch_code\":\"B0000001\",\"received_date\":\"2025-11-17\",\"expiry_date\":\"2026-11-26\",\"batch_quantity_store\":-26,\"last_update_ts\":\"2025-10-01T01:48:40.000Z\"},\"maxValues\":{\"shelf_id\":\"WINWHI0806\",\"batch_code\":\"B0007547\",\"received_date\":\"2025-11-26\",\"expiry_date\":\"2029-10-25\",\"batch_quantity_store\":75,\"last_update_ts\":\"2025-10-03T03:54:05.000Z\"},\"nullCount\":{\"shelf_id\":0,\"batch_code\":0,\"received_date\":0,\"expiry_date\":0,\"batch_quantity_store\":0,\"last_update_ts\":0}}"}}
{"remove":{"path":"part-00000-ee639c54-a47e-4cc1-ba94-8cac587aff06-c000.snappy.parquet","deletionTimestamp":1767544278553,"dataChange":true,"extendedFileMetadata":true,"partitionValues":{},"size":136153,"stats":"{\"numRecords\":7547}"}}
