{"commitInfo":{"timestamp":1767543005825,"operation":"MERGE","operationParameters":{"predicate":"[\"((shelf_id#81587 = shelf_id#81549) AND (batch_code#81588 = batch_code#81550))\"]","matchedPredicates":"[{\"actionType\":\"update\"}]","notMatchedPredicates":"[]","notMatchedBySourcePredicates":"[]"},"readVersion":806,"isolationLevel":"Serializable","isBlindAppend":false,"operationMetrics":{"numTargetRowsCopied":"7416","numTargetRowsDeleted":"0","numTargetFilesAdded":"1","numTargetBytesAdded":"135998","numTargetBytesRemoved":"135978","numTargetDeletionVectorsAdded":"0","numTargetRowsMatchedUpdated":"131","executionTimeMs":"2830","numTargetRowsInserted":"0","numTargetRowsMatchedDeleted":"0","numTargetDeletionVectorsUpdated":"0","scanTimeMs":"1202","numTargetRowsUpdated":"131","numOutputRows":"7547","numTargetDeletionVectorsRemoved":"0","numTargetRowsNotMatchedBySourceUpdated":"0","numTargetChangeFilesAdded":"0","numSourceRows":"131","numTargetFilesRemoved":"1","numTargetRowsNotMatchedBySourceDeleted":"0","rewriteTimeMs":"559"},"engineInfo":"Apache-Spark/3.5.1 Delta-Lake/3.2.0","txnId":"c2dc500a-5728-4e5b-b370-0271e250d1b4"}}
{"add":{"path":"part-00000-e06d25d6-967f-4078-97be-e94bf1fe2e56-c000.snappy.parquet","partitionValues":{},"size":135998,"modificationTime":1767543005807,"dataChange":true,"stats":"{\"numRecords\":7547,\"minValues\":{\"shelf_id\":\"BABBAB2856\",\"batch_code\":\"B0000001\",\"received_date\":\"2025-11-17\",\"expiry_date\":\"2026-11-26\",\"batch_quantity_store\":-26,\"last_update_ts\":\"2025-10-01T01:48:40.000Z\"},\"maxValues\":{\"shelf_id\":\"WINWHI0806\",\"batch_code\":\"B0007547\",\"received_date\":\"2025-11-26\",\"expiry_date\":\"2029-10-25\",\"batch_quantity_store\":75,\"last_update_ts\":\"2025-10-03T03:54:05.000Z\"},\"nullCount\":{\"shelf_id\":0,\"batch_code\":0,\"received_date\":0,\"expiry_date\":0,\"batch_quantity_store\":0,\"last_update_ts\":0}}"}}
{"remove":{"path":"part-00000-fe15afbf-970c-4b75-9017-01a0b8fd3e47-c000.snappy.parquet","deletionTimestamp":1767543005824,"dataChange":true,"extendedFileMetadata":true,"partitionValues":{},"size":135978,"stats":"{\"numRecords\":7547}"}}
