{"commitInfo":{"timestamp":1767536242843,"operation":"MERGE","operationParameters":{"predicate":"[\"((shelf_id#592949 = shelf_id#592911) AND (batch_code#592950 = batch_code#592912))\"]","matchedPredicates":"[{\"actionType\":\"update\"}]","notMatchedPredicates":"[]","notMatchedBySourcePredicates":"[]"},"readVersion":204,"isolationLevel":"Serializable","isBlindAppend":false,"operationMetrics":{"numTargetRowsCopied":"7471","numTargetRowsDeleted":"0","numTargetFilesAdded":"1","numTargetBytesAdded":"127045","numTargetBytesRemoved":"126993","numTargetDeletionVectorsAdded":"0","numTargetRowsMatchedUpdated":"76","executionTimeMs":"1561","numTargetRowsInserted":"0","numTargetRowsMatchedDeleted":"0","numTargetDeletionVectorsUpdated":"0","scanTimeMs":"578","numTargetRowsUpdated":"76","numOutputRows":"7547","numTargetDeletionVectorsRemoved":"0","numTargetRowsNotMatchedBySourceUpdated":"0","numTargetChangeFilesAdded":"0","numSourceRows":"76","numTargetFilesRemoved":"1","numTargetRowsNotMatchedBySourceDeleted":"0","rewriteTimeMs":"136"},"engineInfo":"Apache-Spark/3.5.1 Delta-Lake/3.2.0","txnId":"02b527cf-ff66-49d8-ba0a-9005ec594490"}}
{"add":{"path":"part-00000-de1c977f-a9fb-4b5a-9782-3848e76c1418-c000.snappy.parquet","partitionValues":{},"size":127045,"modificationTime":1767536242840,"dataChange":true,"stats":"{\"numRecords\":7547,\"minValues\":{\"shelf_id\":\"BABBAB2856\",\"batch_code\":\"B0000001\",\"received_date\":\"2025-11-17\",\"expiry_date\":\"2026-11-26\",\"batch_quantity_store\":0,\"last_update_ts\":\"2025-10-01T01:48:40.000Z\"},\"maxValues\":{\"shelf_id\":\"WINWHI0806\",\"batch_code\":\"B0007547\",\"received_date\":\"2025-11-26\",\"expiry_date\":\"2029-10-25\",\"batch_quantity_store\":77,\"last_update_ts\":\"2025-10-02T18:16:05.000Z\"},\"nullCount\":{\"shelf_id\":0,\"batch_code\":0,\"received_date\":0,\"expiry_date\":0,\"batch_quantity_store\":0,\"last_update_ts\":0}}"}}
{"remove":{"path":"part-00000-044bab83-171e-411c-a18a-126f6694e8fd-c000.snappy.parquet","deletionTimestamp":1767536242843,"dataChange":true,"extendedFileMetadata":true,"partitionValues":{},"size":126993,"stats":"{\"numRecords\":7547}"}}
