{"commitInfo":{"timestamp":1767611009617,"operation":"MERGE","operationParameters":{"predicate":"[\"((shelf_id#267305 = shelf_id#267267) AND (batch_code#267306 = batch_code#267268))\"]","matchedPredicates":"[{\"actionType\":\"update\"}]","notMatchedPredicates":"[]","notMatchedBySourcePredicates":"[]"},"readVersion":93,"isolationLevel":"Serializable","isBlindAppend":false,"operationMetrics":{"numTargetRowsCopied":"1628","numTargetRowsDeleted":"0","numTargetFilesAdded":"1","numTargetBytesAdded":"27275","numTargetBytesRemoved":"27260","numTargetDeletionVectorsAdded":"0","numTargetRowsMatchedUpdated":"11","executionTimeMs":"2243","numTargetRowsInserted":"0","numTargetRowsMatchedDeleted":"0","numTargetDeletionVectorsUpdated":"0","scanTimeMs":"1050","numTargetRowsUpdated":"11","numOutputRows":"1639","numTargetDeletionVectorsRemoved":"0","numTargetRowsNotMatchedBySourceUpdated":"0","numTargetChangeFilesAdded":"0","numSourceRows":"11","numTargetFilesRemoved":"1","numTargetRowsNotMatchedBySourceDeleted":"0","rewriteTimeMs":"194"},"engineInfo":"Apache-Spark/3.5.1 Delta-Lake/3.2.0","txnId":"60595795-d046-47a1-85e4-890a29c767da"}}
{"add":{"path":"part-00000-0120efaf-27b4-4cb4-980d-7a82f50d5ec0-c000.snappy.parquet","partitionValues":{},"size":27275,"modificationTime":1767611009611,"dataChange":true,"stats":"{\"numRecords\":1639,\"minValues\":{\"shelf_id\":\"BABBAB0477\",\"batch_code\":\"B0000001\",\"received_date\":\"2025-12-20\",\"expiry_date\":\"2026-01-06\",\"batch_quantity_store\":0,\"last_update_ts\":\"2025-10-01T00:11:20.000Z\"},\"maxValues\":{\"shelf_id\":\"WINWHI0133\",\"batch_code\":\"B0001639\",\"received_date\":\"2026-01-04\",\"expiry_date\":\"2028-11-26\",\"batch_quantity_store\":78,\"last_update_ts\":\"2025-10-01T06:40:35.000Z\"},\"nullCount\":{\"shelf_id\":0,\"batch_code\":0,\"received_date\":0,\"expiry_date\":0,\"batch_quantity_store\":0,\"last_update_ts\":0}}"}}
{"remove":{"path":"part-00000-cf7454aa-dbdb-4d2b-887f-0a1b61ef4415-c000.snappy.parquet","deletionTimestamp":1767611009617,"dataChange":true,"extendedFileMetadata":true,"partitionValues":{},"size":27260,"stats":"{\"numRecords\":1639}"}}
