{"commitInfo":{"timestamp":1767537007325,"operation":"MERGE","operationParameters":{"predicate":"[\"(shelf_id#62138 = shelf_id#1199)\"]","matchedPredicates":"[{\"actionType\":\"update\"}]","notMatchedPredicates":"[{\"actionType\":\"insert\"}]","notMatchedBySourcePredicates":"[]"},"readVersion":395,"isolationLevel":"Serializable","isBlindAppend":false,"operationMetrics":{"numTargetRowsCopied":"6635","numTargetRowsDeleted":"0","numTargetFilesAdded":"1","numTargetBytesAdded":"56979","numTargetBytesRemoved":"56973","numTargetDeletionVectorsAdded":"0","numTargetRowsMatchedUpdated":"65","executionTimeMs":"2040","numTargetRowsInserted":"0","numTargetRowsMatchedDeleted":"0","numTargetDeletionVectorsUpdated":"0","scanTimeMs":"755","numTargetRowsUpdated":"65","numOutputRows":"6700","numTargetDeletionVectorsRemoved":"0","numTargetRowsNotMatchedBySourceUpdated":"0","numTargetChangeFilesAdded":"0","numSourceRows":"65","numTargetFilesRemoved":"1","numTargetRowsNotMatchedBySourceDeleted":"0","rewriteTimeMs":"317"},"engineInfo":"Apache-Spark/3.5.1 Delta-Lake/3.2.0","txnId":"544c43f0-4c7f-4a79-94ce-700ca9cd74e9"}}
{"add":{"path":"part-00000-a69a7e5f-c989-47ca-a6dc-b0bc0c1b1bc8-c000.snappy.parquet","partitionValues":{},"size":56979,"modificationTime":1767537007319,"dataChange":true,"stats":"{\"numRecords\":6700,\"minValues\":{\"shelf_id\":\"BABBAB2856\",\"current_stock\":-16,\"shelf_weight\":10.0,\"last_update_ts\":\"2025-10-01T01:47:50.000Z\"},\"maxValues\":{\"shelf_id\":\"WINWHI0806\",\"current_stock\":94,\"shelf_weight\":5000.0,\"last_update_ts\":\"2025-10-03T04:03:40.000Z\"},\"nullCount\":{\"shelf_id\":0,\"current_stock\":0,\"shelf_weight\":0,\"last_update_ts\":0}}"}}
{"remove":{"path":"part-00000-837b7d1a-ae6a-4100-aad5-5cbea6dd1369-c000.snappy.parquet","deletionTimestamp":1767537007324,"dataChange":true,"extendedFileMetadata":true,"partitionValues":{},"size":56973,"stats":"{\"numRecords\":6700}"}}
