{"commitInfo":{"timestamp":1767537283688,"operation":"MERGE","operationParameters":{"predicate":"[\"(shelf_id#212082 = shelf_id#1199)\"]","matchedPredicates":"[{\"actionType\":\"update\"}]","notMatchedPredicates":"[{\"actionType\":\"insert\"}]","notMatchedBySourcePredicates":"[]"},"readVersion":449,"isolationLevel":"Serializable","isBlindAppend":false,"operationMetrics":{"numTargetRowsCopied":"6629","numTargetRowsDeleted":"0","numTargetFilesAdded":"1","numTargetBytesAdded":"57243","numTargetBytesRemoved":"57235","numTargetDeletionVectorsAdded":"0","numTargetRowsMatchedUpdated":"71","executionTimeMs":"1331","numTargetRowsInserted":"0","numTargetRowsMatchedDeleted":"0","numTargetDeletionVectorsUpdated":"0","scanTimeMs":"682","numTargetRowsUpdated":"71","numOutputRows":"6700","numTargetDeletionVectorsRemoved":"0","numTargetRowsNotMatchedBySourceUpdated":"0","numTargetChangeFilesAdded":"0","numSourceRows":"71","numTargetFilesRemoved":"1","numTargetRowsNotMatchedBySourceDeleted":"0","rewriteTimeMs":"183"},"engineInfo":"Apache-Spark/3.5.1 Delta-Lake/3.2.0","txnId":"cf3631f6-5994-41fa-bc41-bdb8c9c89ee5"}}
{"add":{"path":"part-00000-6ecf437c-ac14-4aa2-9a44-9ddadbb098ed-c000.snappy.parquet","partitionValues":{},"size":57243,"modificationTime":1767537283693,"dataChange":true,"stats":"{\"numRecords\":6700,\"minValues\":{\"shelf_id\":\"BABBAB2856\",\"current_stock\":-18,\"shelf_weight\":10.0,\"last_update_ts\":\"2025-10-01T01:47:50.000Z\"},\"maxValues\":{\"shelf_id\":\"WINWHI0806\",\"current_stock\":93,\"shelf_weight\":5000.0,\"last_update_ts\":\"2025-10-03T04:03:40.000Z\"},\"nullCount\":{\"shelf_id\":0,\"current_stock\":0,\"shelf_weight\":0,\"last_update_ts\":0}}"}}
{"remove":{"path":"part-00000-ec64e8ce-def2-4dcf-9763-050b64f66cd3-c000.snappy.parquet","deletionTimestamp":1767537283688,"dataChange":true,"extendedFileMetadata":true,"partitionValues":{},"size":57235,"stats":"{\"numRecords\":6700}"}}
