{"commitInfo":{"timestamp":1767609492127,"operation":"MERGE","operationParameters":{"predicate":"[\"(shelf_id#195765 = shelf_id#1367)\"]","matchedPredicates":"[{\"actionType\":\"update\"}]","notMatchedPredicates":"[{\"actionType\":\"insert\"}]","notMatchedBySourcePredicates":"[]"},"readVersion":71,"isolationLevel":"Serializable","isBlindAppend":false,"operationMetrics":{"numTargetRowsCopied":"1136","numTargetRowsDeleted":"0","numTargetFilesAdded":"1","numTargetBytesAdded":"12545","numTargetBytesRemoved":"12523","numTargetDeletionVectorsAdded":"0","numTargetRowsMatchedUpdated":"6","executionTimeMs":"2713","numTargetRowsInserted":"0","numTargetRowsMatchedDeleted":"0","numTargetDeletionVectorsUpdated":"0","scanTimeMs":"1174","numTargetRowsUpdated":"6","numOutputRows":"1142","numTargetDeletionVectorsRemoved":"0","numTargetRowsNotMatchedBySourceUpdated":"0","numTargetChangeFilesAdded":"0","numSourceRows":"6","numTargetFilesRemoved":"1","numTargetRowsNotMatchedBySourceDeleted":"0","rewriteTimeMs":"635"},"engineInfo":"Apache-Spark/3.5.1 Delta-Lake/3.2.0","txnId":"c286e90c-c2f8-4b35-a180-17b0f221d430"}}
{"add":{"path":"part-00000-676af559-7a57-4c74-8c61-1422d79630b2-c000.snappy.parquet","partitionValues":{},"size":12545,"modificationTime":1767609492107,"dataChange":true,"stats":"{\"numRecords\":1142,\"minValues\":{\"shelf_id\":\"BABBAB0477\",\"current_stock\":2,\"shelf_weight\":14.0,\"last_update_ts\":\"2025-10-01T00:11:20.000Z\"},\"maxValues\":{\"shelf_id\":\"WINWHI0133\",\"current_stock\":214,\"shelf_weight\":5000.0,\"last_update_ts\":\"2025-10-01T02:32:20.000Z\"},\"nullCount\":{\"shelf_id\":0,\"current_stock\":0,\"shelf_weight\":0,\"last_update_ts\":0}}"}}
{"remove":{"path":"part-00000-a0b14984-276f-473b-90c5-d767960f0f36-c000.snappy.parquet","deletionTimestamp":1767609492121,"dataChange":true,"extendedFileMetadata":true,"partitionValues":{},"size":12523,"stats":"{\"numRecords\":1142}"}}
