{"commitInfo":{"timestamp":1767535081870,"operation":"MERGE","operationParameters":{"predicate":"[\"(shelf_id#161882 = shelf_id#1367)\"]","matchedPredicates":"[{\"actionType\":\"update\"}]","notMatchedPredicates":"[{\"actionType\":\"insert\"}]","notMatchedBySourcePredicates":"[]"},"readVersion":59,"isolationLevel":"Serializable","isBlindAppend":false,"operationMetrics":{"numTargetRowsCopied":"6639","numTargetRowsDeleted":"0","numTargetFilesAdded":"1","numTargetBytesAdded":"51969","numTargetBytesRemoved":"51961","numTargetDeletionVectorsAdded":"0","numTargetRowsMatchedUpdated":"61","executionTimeMs":"1526","numTargetRowsInserted":"0","numTargetRowsMatchedDeleted":"0","numTargetDeletionVectorsUpdated":"0","scanTimeMs":"671","numTargetRowsUpdated":"61","numOutputRows":"6700","numTargetDeletionVectorsRemoved":"0","numTargetRowsNotMatchedBySourceUpdated":"0","numTargetChangeFilesAdded":"0","numSourceRows":"61","numTargetFilesRemoved":"1","numTargetRowsNotMatchedBySourceDeleted":"0","rewriteTimeMs":"409"},"engineInfo":"Apache-Spark/3.5.1 Delta-Lake/3.2.0","txnId":"ee2b1004-2b53-4532-a272-6f4757bb31cf"}}
{"add":{"path":"part-00000-57c80c42-7113-4b58-98e8-f1a91f69c199-c000.snappy.parquet","partitionValues":{},"size":51969,"modificationTime":1767535081867,"dataChange":true,"stats":"{\"numRecords\":6700,\"minValues\":{\"shelf_id\":\"BABBAB2856\",\"current_stock\":-7,\"shelf_weight\":10.0,\"last_update_ts\":\"2025-10-01T01:47:50.000Z\"},\"maxValues\":{\"shelf_id\":\"WINWHI0806\",\"current_stock\":94,\"shelf_weight\":5000.0,\"last_update_ts\":\"2025-10-01T13:25:45.000Z\"},\"nullCount\":{\"shelf_id\":0,\"current_stock\":0,\"shelf_weight\":0,\"last_update_ts\":0}}"}}
{"remove":{"path":"part-00000-2b4a22e7-709b-40c6-9069-316d23a3f23f-c000.snappy.parquet","deletionTimestamp":1767535081869,"dataChange":true,"extendedFileMetadata":true,"partitionValues":{},"size":51961,"stats":"{\"numRecords\":6700}"}}
