{"commitInfo":{"timestamp":1767542947096,"operation":"MERGE","operationParameters":{"predicate":"[\"(shelf_id#80473 = shelf_id#1199)\"]","matchedPredicates":"[{\"actionType\":\"update\"}]","notMatchedPredicates":"[{\"actionType\":\"insert\"}]","notMatchedBySourcePredicates":"[]"},"readVersion":1142,"isolationLevel":"Serializable","isBlindAppend":false,"operationMetrics":{"numTargetRowsCopied":"6625","numTargetRowsDeleted":"0","numTargetFilesAdded":"1","numTargetBytesAdded":"59739","numTargetBytesRemoved":"59739","numTargetDeletionVectorsAdded":"0","numTargetRowsMatchedUpdated":"75","executionTimeMs":"2131","numTargetRowsInserted":"0","numTargetRowsMatchedDeleted":"0","numTargetDeletionVectorsUpdated":"0","scanTimeMs":"990","numTargetRowsUpdated":"75","numOutputRows":"6700","numTargetDeletionVectorsRemoved":"0","numTargetRowsNotMatchedBySourceUpdated":"0","numTargetChangeFilesAdded":"0","numSourceRows":"75","numTargetFilesRemoved":"1","numTargetRowsNotMatchedBySourceDeleted":"0","rewriteTimeMs":"322"},"engineInfo":"Apache-Spark/3.5.1 Delta-Lake/3.2.0","txnId":"c723aa05-8781-442d-a217-12408209a1ba"}}
{"add":{"path":"part-00000-fc5f6192-dcb2-4619-85cf-5b6e5db040ce-c000.snappy.parquet","partitionValues":{},"size":59739,"modificationTime":1767542947089,"dataChange":true,"stats":"{\"numRecords\":6700,\"minValues\":{\"shelf_id\":\"BABBAB2856\",\"current_stock\":-39,\"shelf_weight\":10.0,\"last_update_ts\":\"2025-10-01T01:47:50.000Z\"},\"maxValues\":{\"shelf_id\":\"WINWHI0806\",\"current_stock\":88,\"shelf_weight\":5000.0,\"last_update_ts\":\"2025-10-03T04:03:40.000Z\"},\"nullCount\":{\"shelf_id\":0,\"current_stock\":0,\"shelf_weight\":0,\"last_update_ts\":0}}"}}
{"remove":{"path":"part-00000-195fb334-4924-4e86-a926-a163df22a04d-c000.snappy.parquet","deletionTimestamp":1767542947094,"dataChange":true,"extendedFileMetadata":true,"partitionValues":{},"size":59739,"stats":"{\"numRecords\":6700}"}}
