{"commitInfo":{"timestamp":1767534994006,"operation":"MERGE","operationParameters":{"predicate":"[\"(shelf_id#110431 = shelf_id#1367)\"]","matchedPredicates":"[{\"actionType\":\"update\"}]","notMatchedPredicates":"[{\"actionType\":\"insert\"}]","notMatchedBySourcePredicates":"[]"},"readVersion":40,"isolationLevel":"Serializable","isBlindAppend":false,"operationMetrics":{"numTargetRowsCopied":"6576","numTargetRowsDeleted":"0","numTargetFilesAdded":"1","numTargetBytesAdded":"51494","numTargetBytesRemoved":"51432","numTargetDeletionVectorsAdded":"0","numTargetRowsMatchedUpdated":"124","executionTimeMs":"1509","numTargetRowsInserted":"0","numTargetRowsMatchedDeleted":"0","numTargetDeletionVectorsUpdated":"0","scanTimeMs":"722","numTargetRowsUpdated":"124","numOutputRows":"6700","numTargetDeletionVectorsRemoved":"0","numTargetRowsNotMatchedBySourceUpdated":"0","numTargetChangeFilesAdded":"0","numSourceRows":"124","numTargetFilesRemoved":"1","numTargetRowsNotMatchedBySourceDeleted":"0","rewriteTimeMs":"302"},"engineInfo":"Apache-Spark/3.5.1 Delta-Lake/3.2.0","txnId":"d2623237-186f-4352-a62e-9fc25432ad4d"}}
{"add":{"path":"part-00000-40c40493-5f79-466b-885b-129bccc1737a-c000.snappy.parquet","partitionValues":{},"size":51494,"modificationTime":1767534993987,"dataChange":true,"stats":"{\"numRecords\":6700,\"minValues\":{\"shelf_id\":\"BABBAB2856\",\"current_stock\":-7,\"shelf_weight\":10.0,\"last_update_ts\":\"2025-10-01T01:47:50.000Z\"},\"maxValues\":{\"shelf_id\":\"WINWHI0806\",\"current_stock\":94,\"shelf_weight\":5000.0,\"last_update_ts\":\"2025-10-01T11:14:15.000Z\"},\"nullCount\":{\"shelf_id\":0,\"current_stock\":0,\"shelf_weight\":0,\"last_update_ts\":0}}"}}
{"remove":{"path":"part-00000-8e07eb98-88f4-496e-a344-577d308946d2-c000.snappy.parquet","deletionTimestamp":1767534994006,"dataChange":true,"extendedFileMetadata":true,"partitionValues":{},"size":51432,"stats":"{\"numRecords\":6700}"}}
