{"commitInfo":{"timestamp":1767534790823,"operation":"MERGE","operationParameters":{"predicate":"[\"(shelf_id#70346 = shelf_id#1367)\"]","matchedPredicates":"[{\"actionType\":\"update\"}]","notMatchedPredicates":"[{\"actionType\":\"insert\"}]","notMatchedBySourcePredicates":"[]"},"readVersion":26,"isolationLevel":"Serializable","isBlindAppend":false,"operationMetrics":{"numTargetRowsCopied":"6459","numTargetRowsDeleted":"0","numTargetFilesAdded":"1","numTargetBytesAdded":"49901","numTargetBytesRemoved":"49653","numTargetDeletionVectorsAdded":"0","numTargetRowsMatchedUpdated":"241","executionTimeMs":"4616","numTargetRowsInserted":"0","numTargetRowsMatchedDeleted":"0","numTargetDeletionVectorsUpdated":"0","scanTimeMs":"2032","numTargetRowsUpdated":"241","numOutputRows":"6700","numTargetDeletionVectorsRemoved":"0","numTargetRowsNotMatchedBySourceUpdated":"0","numTargetChangeFilesAdded":"0","numSourceRows":"241","numTargetFilesRemoved":"1","numTargetRowsNotMatchedBySourceDeleted":"0","rewriteTimeMs":"670"},"engineInfo":"Apache-Spark/3.5.1 Delta-Lake/3.2.0","txnId":"66f8bdfb-03c8-4349-bc04-4e9526343d73"}}
{"add":{"path":"part-00000-eab39391-50cd-47bb-8ffb-2f05ef53c9e8-c000.snappy.parquet","partitionValues":{},"size":49901,"modificationTime":1767534790811,"dataChange":true,"stats":"{\"numRecords\":6700,\"minValues\":{\"shelf_id\":\"BABBAB2856\",\"current_stock\":-5,\"shelf_weight\":10.0,\"last_update_ts\":\"2025-10-01T01:47:50.000Z\"},\"maxValues\":{\"shelf_id\":\"WINWHI0806\",\"current_stock\":94,\"shelf_weight\":5000.0,\"last_update_ts\":\"2025-10-01T07:49:05.000Z\"},\"nullCount\":{\"shelf_id\":0,\"current_stock\":0,\"shelf_weight\":0,\"last_update_ts\":0}}"}}
{"remove":{"path":"part-00000-c81af1eb-290f-4705-81e1-309e6087adea-c000.snappy.parquet","deletionTimestamp":1767534790822,"dataChange":true,"extendedFileMetadata":true,"partitionValues":{},"size":49653,"stats":"{\"numRecords\":6700}"}}
